{
  "name": "Lina Howard",
  "age": 64,
  "address": {
    "street": "Novmah Point",
    "city": "Gubgudnan",
    "state": "OR",
    "zip": "63929"
  },
  "contact": {
    "phone": "(666) 503-5041",
    "servicePhone": "800169959"
  },
  "birthday": "1984-02-11T08:09:18.522Z",
  "ip": "64.224.169.143",
  "foo": "bar",
  "profile": {
    "about": "Zumagpe nohuzamo uju omiac mij wek cuvuda zocop pije hug volot maj ed duvizog dogeslu cacafaraj. Da ko tel pub pan bahrav ce lu apuudeleh ucake bituj polbozsi wif mosba haftar. Wab kise fuksoir piv rapo dogu velofupeg be vakazu rucevfa asehidnem now ni. Pedu keemihiv gino ej suz vozub copef maladku azoite la gikhe opitura cav pi. Ugocedom gelpapcuz bo ejonowor reh ihge gogov zokoklev matha cuhuifo kor agsiw taco itejaf zo osugeh. Niv jij pamag oje ufbisis zowgo madkaire bi anope golpop gujpu gu vo oriluf jeb buabnuv.",
    "bio": "Opa valoob iwuc ijo nuon de banat so parpece biakuso vo la gemuf romze. Or ku zubfuvir ziki nu mola hisrekwog ojazi mudjuscu ji lufeblov kesdulu cif lut gefuljoz. Iz bug refutu waitu ka dotvaplul huwseb ufate jedno sam ev vundeboj sipo. Onepoh do mog kez su ipuir veh vikka rivcuit fafap bajec zoda lu agu jejehaari."
  },
  "apiKey": "2315732bdc72e69db3751b452c3f6ec696801a857b6dc4cef7ffff72e036c362",
  "currency": {
    "code": "BZD",
    "name": "Belize Dollar"
  }
}